MANIFEST.in
README.md
requirements.txt
setup.py
test-requirements.txt
amplify_aws_utils/__init__.py
amplify_aws_utils/exceptions.py
amplify_aws_utils/jitter.py
amplify_aws_utils/resource_helper.py
amplify_aws_utils/s3_uri.py
amplify_aws_utils/version.py
amplify_aws_utils.egg-info/PKG-INFO
amplify_aws_utils.egg-info/SOURCES.txt
amplify_aws_utils.egg-info/dependency_links.txt
amplify_aws_utils.egg-info/not-zip-safe
amplify_aws_utils.egg-info/requires.txt
amplify_aws_utils.egg-info/top_level.txt
amplify_aws_utils/clients/__init__.py
amplify_aws_utils/clients/config.py
amplify_aws_utils/clients/ec2.py
amplify_aws_utils/clients/s3.py
amplify_aws_utils/clients/spotinst.py
amplify_aws_utils/clients/sts.py