Metadata-Version: 2.4
Name: amplify_aws_utils
Version: 0.6.0
Summary: Utility functions for working with AWS resources
Home-page: https://github.com/amplify-education/amplify_aws_utils/
Author: Amplify Education
Author-email: astrotools@amplify.com
License: MIT
Classifier: Topic :: Software Development :: Libraries :: Python Modules
Classifier: Programming Language :: Python
Classifier: Programming Language :: Python :: 3
Classifier: Programming Language :: Python :: 3.8
Classifier: Programming Language :: Python :: 3.9
Classifier: Programming Language :: Python :: 3.10
Classifier: Programming Language :: Python :: 3.11
Classifier: Programming Language :: Python :: 3.12
Requires-Python: >=3.8.0
Requires-Dist: aws-lambda-powertools~=3.0
Requires-Dist: boto3~=1.34
Requires-Dist: boto3-stubs[config,ec2,s3,ssm,sts]~=1.34
Requires-Dist: requests~=2.31
Dynamic: author
Dynamic: author-email
Dynamic: classifier
Dynamic: description
Dynamic: description-content-type
Dynamic: home-page
Dynamic: keywords
Dynamic: license
Dynamic: requires-dist
Dynamic: requires-python
Dynamic: summary
